assists/__init__.py
assists/cloud/__init__.py
assists/cloud/aws.py
assists/cloud/azure.py
assists/main.py
assists/tools/__init__.py
assists/tools/terraform.py
assists-0.2.0.dist-info/LICENSE.txt
assists-0.2.0.dist-info/METADATA
assists-0.2.0.dist-info/WHEEL
assists-0.2.0.dist-info/entry_points.txt
assists-0.2.0.dist-info/RECORD
